CHANGES.rst
DESCRIPTION.rst
LICENSE
MANIFEST.in
README.md
setup.py
src/wai/logging/__init__.py
src/wai/logging/_argparse.py
src/wai/logging/_core.py
src/wai_logging.egg-info/PKG-INFO
src/wai_logging.egg-info/SOURCES.txt
src/wai_logging.egg-info/dependency_links.txt
src/wai_logging.egg-info/top_level.txt